idun_mock/__init__.py
idun_mock/client/__init__.py
idun_mock/client/__main__.py
idun_mock/data_generator/__init__.py
idun_mock/data_generator/connection_pool.py
idun_mock/data_generator/generator.py
idun_mock/data_generator/igeb_test_packets-0.txt
idun_mock/data_generator/igeb_test_packets.txt
idun_mock-0.1.5.dist-info/METADATA
idun_mock-0.1.5.dist-info/WHEEL
idun_mock-0.1.5.dist-info/RECORD
