Metadata-Version: 2.1
Name: idun_mock
Version: 0.1.5
Summary: Mock a real IDUN Guardian device for testing purposes
Author: Konstantinos Samaras-Tsakiris
Author-email: konstantinos@iduntechnologies.com
Requires-Python: >=3.10,<4.0
Classifier: Programming Language :: Python :: 3
Classifier: Programming Language :: Python :: 3.10
Classifier: Programming Language :: Python :: 3.11
Requires-Dist: boto3 (>=1.28,<2.0)
Requires-Dist: dacite (>=1.8,<2.0)
Requires-Dist: httpx (>=0.25,<0.26)
Requires-Dist: idun_data_models (>=0.3.0,<0.4.0)
Requires-Dist: idun_tools (>=0.1.0,<0.2.0)
Requires-Dist: websockets (>=11.0,<12.0)
